office_word_count/__init__.py
office_word_count/counter.py
office_word_count/patterns.py
office_word_count/statistics.py
office_word_count/text.py
office_word_count-0.1.2.dist-info/LICENSE.txt
office_word_count-0.1.2.dist-info/METADATA
office_word_count-0.1.2.dist-info/WHEEL
office_word_count-0.1.2.dist-info/top_level.txt
office_word_count-0.1.2.dist-info/RECORD
