Metadata-Version: 2.1
Name: office-word-count
Version: 0.1.2
Summary: Word count tool like MS Office Word
Home-page: https://github.com/bebe3/office-word-count
Author: bebe3
Author-email: i.masashi0323@gmail.com
License: MIT
Classifier: License :: OSI Approved :: MIT License
Classifier: Programming Language :: Python :: 3.8
Classifier: Programming Language :: Python :: 3.9
Classifier: Programming Language :: Python :: 3.10
License-File: LICENSE.txt
Requires-Dist: regex
